{
  "alias": null,
  "name": "hs_hr_employee",
  "label": "Hs Hr Employee",
  "description": null,
  "native": [],
  "plural": "Hs Hr Employees",
  "is_view": false,
  "primary_key": [
    "emp_number"
  ],
  "name_field": null,
  "field": [
    {
      "alias": null,
      "name": "emp_number",
      "label": "Emp Number",
      "description": null,
      "native": [],
      "type": "integer",
      "db_type": "int(7)",
      "length": 7,
      "precision": null,
      "scale": null,
      "default": 0,
      "required": false,
      "allow_null": false,
      "fixed_length": false,
      "supports_multibyte": false,
      "auto_increment": false,
      "is_primary_key": true,
      "is_unique": false,
      "is_index": false,
      "is_foreign_key": false,
      "ref_table": null,
      "ref_field": null,
      "ref_on_update": null,
      "ref_on_delete": null,
      "picklist": null,
      "validation": null,
      "db_function": null,
      "is_virtual": false,
      "is_aggregate": false
    },
    {
      "alias": null,
      "name": "employee_id",
      "label": "Employee Id",
      "description": null,
      "native": [],
      "type": "string",
      "db_type": "varchar(50)",
      "length": 50,
      "precision": null,
      "scale": null,
      "default": null,
      "required": false,
      "allow_null": true,
      "fixed_length": false,
      "supports_multibyte": true,
      "auto_increment": false,
      "is_primary_key": false,
      "is_unique": false,
      "is_index": false,
      "is_foreign_key": false,
      "ref_table": null,
      "ref_field": null,
      "ref_on_update": null,
      "ref_on_delete": null,
      "picklist": null,
      "validation": null,
      "db_function": null,
      "is_virtual": false,
      "is_aggregate": false
    },
    {
      "alias": null,
      "name": "emp_lastname",
      "label": "Emp Lastname",
      "description": null,
      "native": [],
      "type": "string",
      "db_type": "varchar(100)",
      "length": 100,
      "precision": null,
      "scale": null,
      "default": "",
      "required": false,
      "allow_null": false,
      "fixed_length": false,
      "supports_multibyte": true,
      "auto_increment": false,
      "is_primary_key": false,
      "is_unique": false,
      "is_index": false,
      "is_foreign_key": false,
      "ref_table": null,
      "ref_field": null,
      "ref_on_update": null,
      "ref_on_delete": null,
      "picklist": null,
      "validation": null,
      "db_function": null,
      "is_virtual": false,
      "is_aggregate": false
    },
    {
      "alias": null,
      "name": "emp_firstname",
      "label": "Emp Firstname",
      "description": null,
      "native": [],
      "type": "string",
      "db_type": "varchar(100)",
      "length": 100,
      "precision": null,
      "scale": null,
      "default": "",
      "required": false,
      "allow_null": false,
      "fixed_length": false,
      "supports_multibyte": true,
      "auto_increment": false,
      "is_primary_key": false,
      "is_unique": false,
      "is_index": false,
      "is_foreign_key": false,
      "ref_table": null,
      "ref_field": null,
      "ref_on_update": null,
      "ref_on_delete": null,
      "picklist": null,
      "validation": null,
      "db_function": null,
      "is_virtual": false,
      "is_aggregate": false
    },
    {
      "alias": null,
      "name": "emp_middle_name",
      "label": "Emp Middle Name",
      "description": null,
      "native": [],
      "type": "string",
      "db_type": "varchar(100)",
      "length": 100,
      "precision": null,
      "scale": null,
      "default": "",
      "required": false,
      "allow_null": false,
      "fixed_length": false,
      "supports_multibyte": true,
      "auto_increment": false,
      "is_primary_key": false,
      "is_unique": false,
      "is_index": false,
      "is_foreign_key": false,
      "ref_table": null,
      "ref_field": null,
      "ref_on_update": null,
      "ref_on_delete": null,
      "picklist": null,
      "validation": null,
      "db_function": null,
      "is_virtual": false,
      "is_aggregate": false
    },
    {
      "alias": null,
      "name": "emp_nick_name",
      "label": "Emp Nick Name",
      "description": null,
      "native": [],
      "type": "string",
      "db_type": "varchar(100)",
      "length": 100,
      "precision": null,
      "scale": null,
      "default": "",
      "required": false,
      "allow_null": true,
      "fixed_length": false,
      "supports_multibyte": true,
      "auto_increment": false,
      "is_primary_key": false,
      "is_unique": false,
      "is_index": false,
      "is_foreign_key": false,
      "ref_table": null,
      "ref_field": null,
      "ref_on_update": null,
      "ref_on_delete": null,
      "picklist": null,
      "validation": null,
      "db_function": null,
      "is_virtual": false,
      "is_aggregate": false
    },
   
    
    {
      "alias": null,
      "name": "emp_birthday",
      "label": "Emp Birthday",
      "description": null,
      "native": [],
      "type": "date",
      "db_type": "date",
      "length": null,
      "precision": null,
      "scale": null,
      "default": null,
      "required": false,
      "allow_null": true,
      "fixed_length": false,
      "supports_multibyte": false,
      "auto_increment": false,
      "is_primary_key": false,
      "is_unique": false,
      "is_index": false,
      "is_foreign_key": false,
      "ref_table": null,
      "ref_field": null,
      "ref_on_update": null,
      "ref_on_delete": null,
      "picklist": null,
      "validation": null,
      "db_function": null,
      "is_virtual": false,
      "is_aggregate": false
    },
    {
      "alias": null,
      "name": "nation_code",
      "label": "Nation Code",
      "description": null,
      "native": [],
      "type": "reference",
      "db_type": "int(4)",
      "length": 4,
      "precision": null,
      "scale": null,
      "default": null,
      "required": false,
      "allow_null": true,
      "fixed_length": false,
      "supports_multibyte": false,
      "auto_increment": false,
      "is_primary_key": false,
      "is_unique": false,
      "is_index": true,
      "is_foreign_key": true,
      "ref_table": "ohrm_nationality",
      "ref_field": "id",
      "ref_on_update": null,
      "ref_on_delete": null,
      "picklist": null,
      "validation": null,
      "db_function": null,
      "is_virtual": false,
      "is_aggregate": false
    },
    {
      "alias": null,
      "name": "emp_gender",
      "label": "Emp Gender",
      "description": null,
      "native": [],
      "type": "integer",
      "db_type": "smallint(6)",
      "length": 6,
      "precision": null,
      "scale": null,
      "default": null,
      "required": false,
      "allow_null": true,
      "fixed_length": false,
      "supports_multibyte": false,
      "auto_increment": false,
      "is_primary_key": false,
      "is_unique": false,
      "is_index": false,
      "is_foreign_key": false,
      "ref_table": null,
      "ref_field": null,
      "ref_on_update": null,
      "ref_on_delete": null,
      "picklist": null,
      "validation": null,
      "db_function": null,
      "is_virtual": false,
      "is_aggregate": false
    },
    {
      "alias": null,
      "name": "emp_marital_status",
      "label": "Emp Marital Status",
      "description": null,
      "native": [],
      "type": "string",
      "db_type": "varchar(20)",
      "length": 20,
      "precision": null,
      "scale": null,
      "default": null,
      "required": false,
      "allow_null": true,
      "fixed_length": false,
      "supports_multibyte": true,
      "auto_increment": false,
      "is_primary_key": false,
      "is_unique": false,
      "is_index": false,
      "is_foreign_key": false,
      "ref_table": null,
      "ref_field": null,
      "ref_on_update": null,
      "ref_on_delete": null,
      "picklist": null,
      "validation": null,
      "db_function": null,
      "is_virtual": false,
      "is_aggregate": false
    },
    {
      "alias": null,
      "name": "emp_ssn_num",
      "label": "Emp Ssn Num",
      "description": null,
      "native": [],
      "type": "string",
      "db_type": "varchar(100)",
      "length": 100,
      "precision": null,
      "scale": null,
      "default": "",
      "required": false,
      "allow_null": true,
      "fixed_length": false,
      "supports_multibyte": false,
      "auto_increment": false,
      "is_primary_key": false,
      "is_unique": false,
      "is_index": false,
      "is_foreign_key": false,
      "ref_table": null,
      "ref_field": null,
      "ref_on_update": null,
      "ref_on_delete": null,
      "picklist": null,
      "validation": null,
      "db_function": null,
      "is_virtual": false,
      "is_aggregate": false
    },
    
    {
      "alias": null,
      "name": "emp_dri_lice_num",
      "label": "Emp Dri Lice Num",
      "description": null,
      "native": [],
      "type": "string",
      "db_type": "varchar(100)",
      "length": 100,
      "precision": null,
      "scale": null,
      "default": "",
      "required": false,
      "allow_null": true,
      "fixed_length": false,
      "supports_multibyte": true,
      "auto_increment": false,
      "is_primary_key": false,
      "is_unique": false,
      "is_index": false,
      "is_foreign_key": false,
      "ref_table": null,
      "ref_field": null,
      "ref_on_update": null,
      "ref_on_delete": null,
      "picklist": null,
      "validation": null,
      "db_function": null,
      "is_virtual": false,
      "is_aggregate": false
    },
    {
      "alias": null,
      "name": "emp_dri_lice_exp_date",
      "label": "Emp Dri Lice Exp Date",
      "description": null,
      "native": [],
      "type": "date",
      "db_type": "date",
      "length": null,
      "precision": null,
      "scale": null,
      "default": null,
      "required": false,
      "allow_null": true,
      "fixed_length": false,
      "supports_multibyte": false,
      "auto_increment": false,
      "is_primary_key": false,
      "is_unique": false,
      "is_index": false,
      "is_foreign_key": false,
      "ref_table": null,
      "ref_field": null,
      "ref_on_update": null,
      "ref_on_delete": null,
      "picklist": null,
      "validation": null,
      "db_function": null,
      "is_virtual": false,
      "is_aggregate": false
    },
    {
      "alias": null,
      "name": "emp_military_service",
      "label": "Emp Military Service",
      "description": null,
      "native": [],
      "type": "string",
      "db_type": "varchar(100)",
      "length": 100,
      "precision": null,
      "scale": null,
      "default": "",
      "required": false,
      "allow_null": true,
      "fixed_length": false,
      "supports_multibyte": true,
      "auto_increment": false,
      "is_primary_key": false,
      "is_unique": false,
      "is_index": false,
      "is_foreign_key": false,
      "ref_table": null,
      "ref_field": null,
      "ref_on_update": null,
      "ref_on_delete": null,
      "picklist": null,
      "validation": null,
      "db_function": null,
      "is_virtual": false,
      "is_aggregate": false
    },
    {
      "alias": null,
      "name": "emp_status",
      "label": "Emp Status",
      "description": null,
      "native": [],
      "type": "reference",
      "db_type": "int(13)",
      "length": 13,
      "precision": null,
      "scale": null,
      "default": null,
      "required": false,
      "allow_null": true,
      "fixed_length": false,
      "supports_multibyte": false,
      "auto_increment": false,
      "is_primary_key": false,
      "is_unique": false,
      "is_index": true,
      "is_foreign_key": true,
      "ref_table": "ohrm_employment_status",
      "ref_field": "id",
      "ref_on_update": null,
      "ref_on_delete": null,
      "picklist": null,
      "validation": null,
      "db_function": null,
      "is_virtual": false,
      "is_aggregate": false
    },
    {
      "alias": null,
      "name": "job_title_code",
      "label": "Job Title Code",
      "description": null,
      "native": [],
      "type": "reference",
      "db_type": "int(7)",
      "length": 7,
      "precision": null,
      "scale": null,
      "default": null,
      "required": false,
      "allow_null": true,
      "fixed_length": false,
      "supports_multibyte": false,
      "auto_increment": false,
      "is_primary_key": false,
      "is_unique": false,
      "is_index": true,
      "is_foreign_key": true,
      "ref_table": "ohrm_job_title",
      "ref_field": "id",
      "ref_on_update": null,
      "ref_on_delete": null,
      "picklist": null,
      "validation": null,
      "db_function": null,
      "is_virtual": false,
      "is_aggregate": false
    },
    {
      "alias": null,
      "name": "eeo_cat_code",
      "label": "Eeo Cat Code",
      "description": null,
      "native": [],
      "type": "reference",
      "db_type": "int(11)",
      "length": 11,
      "precision": null,
      "scale": null,
      "default": null,
      "required": false,
      "allow_null": true,
      "fixed_length": false,
      "supports_multibyte": false,
      "auto_increment": false,
      "is_primary_key": false,
      "is_unique": false,
      "is_index": true,
      "is_foreign_key": true,
      "ref_table": "ohrm_job_category",
      "ref_field": "id",
      "ref_on_update": null,
      "ref_on_delete": null,
      "picklist": null,
      "validation": null,
      "db_function": null,
      "is_virtual": false,
      "is_aggregate": false
    },
    {
      "alias": null,
      "name": "work_station",
      "label": "Work Station",
      "description": null,
      "native": [],
      "type": "reference",
      "db_type": "int(6)",
      "length": 6,
      "precision": null,
      "scale": null,
      "default": null,
      "required": false,
      "allow_null": true,
      "fixed_length": false,
      "supports_multibyte": false,
      "auto_increment": false,
      "is_primary_key": false,
      "is_unique": false,
      "is_index": true,
      "is_foreign_key": true,
      "ref_table": "ohrm_subunit",
      "ref_field": "id",
      "ref_on_update": null,
      "ref_on_delete": null,
      "picklist": null,
      "validation": null,
      "db_function": null,
      "is_virtual": false,
      "is_aggregate": false
    },
    {
      "alias": null,
      "name": "emp_street1",
      "label": "Emp Street1",
      "description": null,
      "native": [],
      "type": "string",
      "db_type": "varchar(100)",
      "length": 100,
      "precision": null,
      "scale": null,
      "default": "",
      "required": false,
      "allow_null": true,
      "fixed_length": false,
      "supports_multibyte": true,
      "auto_increment": false,
      "is_primary_key": false,
      "is_unique": false,
      "is_index": false,
      "is_foreign_key": false,
      "ref_table": null,
      "ref_field": null,
      "ref_on_update": null,
      "ref_on_delete": null,
      "picklist": null,
      "validation": null,
      "db_function": null,
      "is_virtual": false,
      "is_aggregate": false
    },
    {
      "alias": null,
      "name": "emp_street2",
      "label": "Emp Street2",
      "description": null,
      "native": [],
      "type": "string",
      "db_type": "varchar(100)",
      "length": 100,
      "precision": null,
      "scale": null,
      "default": "",
      "required": false,
      "allow_null": true,
      "fixed_length": false,
      "supports_multibyte": true,
      "auto_increment": false,
      "is_primary_key": false,
      "is_unique": false,
      "is_index": false,
      "is_foreign_key": false,
      "ref_table": null,
      "ref_field": null,
      "ref_on_update": null,
      "ref_on_delete": null,
      "picklist": null,
      "validation": null,
      "db_function": null,
      "is_virtual": false,
      "is_aggregate": false
    },
    {
      "alias": null,
      "name": "city_code",
      "label": "City Code",
      "description": null,
      "native": [],
      "type": "string",
      "db_type": "varchar(100)",
      "length": 100,
      "precision": null,
      "scale": null,
      "default": "",
      "required": false,
      "allow_null": true,
      "fixed_length": false,
      "supports_multibyte": true,
      "auto_increment": false,
      "is_primary_key": false,
      "is_unique": false,
      "is_index": false,
      "is_foreign_key": false,
      "ref_table": null,
      "ref_field": null,
      "ref_on_update": null,
      "ref_on_delete": null,
      "picklist": null,
      "validation": null,
      "db_function": null,
      "is_virtual": false,
      "is_aggregate": false
    },
    {
      "alias": null,
      "name": "coun_code",
      "label": "Coun Code",
      "description": null,
      "native": [],
      "type": "string",
      "db_type": "varchar(100)",
      "length": 100,
      "precision": null,
      "scale": null,
      "default": "",
      "required": false,
      "allow_null": true,
      "fixed_length": false,
      "supports_multibyte": true,
      "auto_increment": false,
      "is_primary_key": false,
      "is_unique": false,
      "is_index": false,
      "is_foreign_key": false,
      "ref_table": null,
      "ref_field": null,
      "ref_on_update": null,
      "ref_on_delete": null,
      "picklist": null,
      "validation": null,
      "db_function": null,
      "is_virtual": false,
      "is_aggregate": false
    },
    {
      "alias": null,
      "name": "provin_code",
      "label": "Provin Code",
      "description": null,
      "native": [],
      "type": "string",
      "db_type": "varchar(100)",
      "length": 100,
      "precision": null,
      "scale": null,
      "default": "",
      "required": false,
      "allow_null": true,
      "fixed_length": false,
      "supports_multibyte": true,
      "auto_increment": false,
      "is_primary_key": false,
      "is_unique": false,
      "is_index": false,
      "is_foreign_key": false,
      "ref_table": null,
      "ref_field": null,
      "ref_on_update": null,
      "ref_on_delete": null,
      "picklist": null,
      "validation": null,
      "db_function": null,
      "is_virtual": false,
      "is_aggregate": false
    },
    {
      "alias": null,
      "name": "emp_zipcode",
      "label": "Emp Zipcode",
      "description": null,
      "native": [],
      "type": "string",
      "db_type": "varchar(20)",
      "length": 20,
      "precision": null,
      "scale": null,
      "default": null,
      "required": false,
      "allow_null": true,
      "fixed_length": false,
      "supports_multibyte": true,
      "auto_increment": false,
      "is_primary_key": false,
      "is_unique": false,
      "is_index": false,
      "is_foreign_key": false,
      "ref_table": null,
      "ref_field": null,
      "ref_on_update": null,
      "ref_on_delete": null,
      "picklist": null,
      "validation": null,
      "db_function": null,
      "is_virtual": false,
      "is_aggregate": false
    },
    {
      "alias": null,
      "name": "emp_hm_telephone",
      "label": "Emp Hm Telephone",
      "description": null,
      "native": [],
      "type": "string",
      "db_type": "varchar(50)",
      "length": 50,
      "precision": null,
      "scale": null,
      "default": null,
      "required": false,
      "allow_null": true,
      "fixed_length": false,
      "supports_multibyte": true,
      "auto_increment": false,
      "is_primary_key": false,
      "is_unique": false,
      "is_index": false,
      "is_foreign_key": false,
      "ref_table": null,
      "ref_field": null,
      "ref_on_update": null,
      "ref_on_delete": null,
      "picklist": null,
      "validation": null,
      "db_function": null,
      "is_virtual": false,
      "is_aggregate": false
    },
    {
      "alias": null,
      "name": "emp_mobile",
      "label": "Emp Mobile",
      "description": null,
      "native": [],
      "type": "string",
      "db_type": "varchar(50)",
      "length": 50,
      "precision": null,
      "scale": null,
      "default": null,
      "required": false,
      "allow_null": true,
      "fixed_length": false,
      "supports_multibyte": true,
      "auto_increment": false,
      "is_primary_key": false,
      "is_unique": false,
      "is_index": false,
      "is_foreign_key": false,
      "ref_table": null,
      "ref_field": null,
      "ref_on_update": null,
      "ref_on_delete": null,
      "picklist": null,
      "validation": null,
      "db_function": null,
      "is_virtual": false,
      "is_aggregate": false
    },
    {
      "alias": null,
      "name": "emp_work_telephone",
      "label": "Emp Work Telephone",
      "description": null,
      "native": [],
      "type": "string",
      "db_type": "varchar(50)",
      "length": 50,
      "precision": null,
      "scale": null,
      "default": null,
      "required": false,
      "allow_null": true,
      "fixed_length": false,
      "supports_multibyte": true,
      "auto_increment": false,
      "is_primary_key": false,
      "is_unique": false,
      "is_index": false,
      "is_foreign_key": false,
      "ref_table": null,
      "ref_field": null,
      "ref_on_update": null,
      "ref_on_delete": null,
      "picklist": null,
      "validation": null,
      "db_function": null,
      "is_virtual": false,
      "is_aggregate": false
    },
    {
      "alias": null,
      "name": "emp_work_email",
      "label": "Emp Work Email",
      "description": null,
      "native": [],
      "type": "string",
      "db_type": "varchar(50)",
      "length": 50,
      "precision": null,
      "scale": null,
      "default": null,
      "required": false,
      "allow_null": true,
      "fixed_length": false,
      "supports_multibyte": true,
      "auto_increment": false,
      "is_primary_key": false,
      "is_unique": false,
      "is_index": false,
      "is_foreign_key": false,
      "ref_table": null,
      "ref_field": null,
      "ref_on_update": null,
      "ref_on_delete": null,
      "picklist": null,
      "validation": null,
      "db_function": null,
      "is_virtual": false,
      "is_aggregate": false
    },
    {
      "alias": null,
      "name": "sal_grd_code",
      "label": "Sal Grd Code",
      "description": null,
      "native": [],
      "type": "string",
      "db_type": "varchar(13)",
      "length": 13,
      "precision": null,
      "scale": null,
      "default": null,
      "required": false,
      "allow_null": true,
      "fixed_length": false,
      "supports_multibyte": true,
      "auto_increment": false,
      "is_primary_key": false,
      "is_unique": false,
      "is_index": false,
      "is_foreign_key": false,
      "ref_table": null,
      "ref_field": null,
      "ref_on_update": null,
      "ref_on_delete": null,
      "picklist": null,
      "validation": null,
      "db_function": null,
      "is_virtual": false,
      "is_aggregate": false
    },
    {
      "alias": null,
      "name": "joined_date",
      "label": "Joined Date",
      "description": null,
      "native": [],
      "type": "date",
      "db_type": "date",
      "length": null,
      "precision": null,
      "scale": null,
      "default": null,
      "required": false,
      "allow_null": true,
      "fixed_length": false,
      "supports_multibyte": false,
      "auto_increment": false,
      "is_primary_key": false,
      "is_unique": false,
      "is_index": false,
      "is_foreign_key": false,
      "ref_table": null,
      "ref_field": null,
      "ref_on_update": null,
      "ref_on_delete": null,
      "picklist": null,
      "validation": null,
      "db_function": null,
      "is_virtual": false,
      "is_aggregate": false
    },
    {
      "alias": null,
      "name": "emp_oth_email",
      "label": "Emp Oth Email",
      "description": null,
      "native": [],
      "type": "string",
      "db_type": "varchar(50)",
      "length": 50,
      "precision": null,
      "scale": null,
      "default": null,
      "required": false,
      "allow_null": true,
      "fixed_length": false,
      "supports_multibyte": true,
      "auto_increment": false,
      "is_primary_key": false,
      "is_unique": false,
      "is_index": false,
      "is_foreign_key": false,
      "ref_table": null,
      "ref_field": null,
      "ref_on_update": null,
      "ref_on_delete": null,
      "picklist": null,
      "validation": null,
      "db_function": null,
      "is_virtual": false,
      "is_aggregate": false
    },
    {
      "alias": null,
      "name": "termination_id",
      "label": "Termination Id",
      "description": null,
      "native": [],
      "type": "reference",
      "db_type": "int(4)",
      "length": 4,
      "precision": null,
      "scale": null,
      "default": null,
      "required": false,
      "allow_null": true,
      "fixed_length": false,
      "supports_multibyte": false,
      "auto_increment": false,
      "is_primary_key": false,
      "is_unique": false,
      "is_index": true,
      "is_foreign_key": true,
      "ref_table": "ohrm_emp_termination",
      "ref_field": "id",
      "ref_on_update": null,
      "ref_on_delete": null,
      "picklist": null,
      "validation": null,
      "db_function": null,
      "is_virtual": false,
      "is_aggregate": false
    }
  ],
  "access": 31
}